LICENSE
MANIFEST.in
README.rst
setup.py
test.py
geo/__init__.py
geo/_ellipsoid.c
geo/_ellipsoid.pyx
geo/_helpers.pxd
geo/_sphere.c
geo/_sphere.pyx
geo/constants.py
geo/ellipsoid.py
geo/sphere.py
geo_py.egg-info/PKG-INFO
geo_py.egg-info/SOURCES.txt
geo_py.egg-info/dependency_links.txt
geo_py.egg-info/top_level.txt