Metadata-Version: 1.1
Name: geo-py
Version: 0.4
Summary: Set of algorithms and structures related to geodesy and geospatial data
Home-page: https://github.com/gojuno/geo-py
Author: Alexander Verbitsky
Author-email: habibutsu@gmail.com
License: BSD
Keywords: geodesy,haversine distance,great circle distance,vincenty's formula
Platform: UNKNOWN
Classifier: Development Status :: 5 - Production/Stable
Classifier: Topic :: Utilities
Classifier: Programming Language :: Python
Classifier: License :: OSI Approved :: BSD License
